<?xml version="1.0" encoding="UTF-8"?>
<messagebundle>
  <msg name="title">De Herinneringen van de verjaardag</msg>
  <msg name="description">Mis opnieuw de verjaardagen nooit van uw vrienden!</msg>
  <msg name="titleName">Titel</msg>
  <msg name="birthdayName">Verjaardagen</msg>
  <msg name="showName">Zichtbare Verjaardagen</msg>
  <msg name="noticeName">Het Bericht van dagen</msg>
  <msg name="tableDate">Datum</msg>
  <msg name="tableName">Naam</msg>
  <msg name="tableAge">Leeftijd</msg>
  <msg name="none">Geen verjaardagen aan vertoning, te voegen gelieve de verjaardagen toe u zich wilt herinneren.</msg>
  <msg name="nobd1">Geen verjaardagen die omhoog in de volgende </msg>
  <msg name="nobd2"> dagen komen.</msg>
  <msg name="ajan">jan</msg>
  <msg name="afeb">feb</msg>
  <msg name="amar">mrt</msg>
  <msg name="aapr">apr</msg>
  <msg name="amay">mei</msg>
  <msg name="ajun">jun</msg>
  <msg name="ajul">jul</msg>
  <msg name="aaug">aug</msg>
  <msg name="asep">sep.</msg>
  <msg name="aoct">okt</msg>
  <msg name="anov">nov</msg>
  <msg name="adec">dec</msg>
  <msg name="trans">*Onjuiste vertaling?*</msg>
  <msg name="today">Vandaag</msg>
  <msg name="formatName">Het Formaat van de datum</msg>
  <msg name="confirmSave">Ga verder zonder besparing?</msg>
  <msg name="modeTitleDisplay">Vertoning</msg>
  <msg name="modeTitleEdit">Geef uit</msg>
  <msg name="buttonSave">Sparen</msg>
  <msg name="boxTitleError">Fout</msg>
  <msg name="errMonth">Ongeldige maand</msg>
  <msg name="errDay">Ongeldige dag</msg>
  <msg name="errFormat">Ondersteund niet formaat</msg>
  <msg name="errName">Gevonden niet naam</msg>
  <msg name="errNameChar">'|' toegestaan niet in Naam</msg>
  <msg name="errLine">Slechts één ';' per lijn</msg>
  <msg name="errDate">Onjuiste Datum</msg>
  <msg name="boxTitlePreview">Voorproef</msg>
  <msg name="format">Formaat: YYYY/MM/DD;Naam of MM/DD;Naam</msg>
  <msg name="warnOver">Waarschuwing! De maximum Bereikte Karakters, te schrappen gelieve wat./msg>
</messagebundle>
